openinference/instrumentation/beeai/__init__.py
openinference/instrumentation/beeai/_span.py
openinference/instrumentation/beeai/_utils.py
openinference/instrumentation/beeai/version.py
openinference/instrumentation/beeai/processors/__init__.py
openinference/instrumentation/beeai/processors/base.py
openinference/instrumentation/beeai/processors/chat.py
openinference/instrumentation/beeai/processors/embedding.py
openinference/instrumentation/beeai/processors/locator.py
openinference/instrumentation/beeai/processors/requirement.py
openinference/instrumentation/beeai/processors/tool.py
openinference/instrumentation/beeai/processors/workflow.py
openinference/instrumentation/beeai/processors/agents/__init__.py
openinference/instrumentation/beeai/processors/agents/base.py
openinference/instrumentation/beeai/processors/agents/react.py
openinference/instrumentation/beeai/processors/agents/requirement_agent.py
openinference/instrumentation/beeai/processors/agents/tool_calling.py
openinference_instrumentation_beeai-0.1.14.dist-info/METADATA
openinference_instrumentation_beeai-0.1.14.dist-info/WHEEL
openinference_instrumentation_beeai-0.1.14.dist-info/entry_points.txt
openinference_instrumentation_beeai-0.1.14.dist-info/RECORD
