Metadata-Version: 2.4
Name: openinference-instrumentation-beeai
Version: 0.1.14
Summary: OpenInference BeeAI Instrumentation
Project-URL: Homepage, https://github.com/Arize-ai/openinference/tree/main/python/instrumentation/openinference-instrumentation-beeai
Author: IBM Corp.
Maintainer-email: Tomas Dvorak <toomas2d@gmail.com>
License-Expression: Apache-2.0
Classifier: Development Status :: 5 - Production/Stable
Classifier: Intended Audience :: Developers
Classifier: License :: OSI Approved :: Apache Software License
Classifier: Programming Language :: Python
Classifier: Programming Language :: Python :: 3
Classifier: Programming Language :: Python :: 3.11
Classifier: Programming Language :: Python :: 3.12
Classifier: Programming Language :: Python :: 3.13
Classifier: Programming Language :: Python :: 3.14
Requires-Python: <3.15,>=3.11
Requires-Dist: beeai-framework<0.2.0,>=0.1.51
Requires-Dist: openinference-instrumentation>=0.1.37
Requires-Dist: openinference-semantic-conventions>=0.1.25
Requires-Dist: opentelemetry-api>=1.36.0
Requires-Dist: opentelemetry-instrumentation>=0.57b0
Requires-Dist: opentelemetry-semantic-conventions>=0.57b0
Requires-Dist: wrapt>=1.17.2
Provides-Extra: instruments
Requires-Dist: beeai-framework>=0.1.51; extra == 'instruments'
Provides-Extra: test
Requires-Dist: beeai-framework>=0.1.51; extra == 'test'
Requires-Dist: opentelemetry-exporter-otlp; extra == 'test'
Requires-Dist: opentelemetry-sdk; extra == 'test'
